ngenctl/__init__.py
ngenctl/cli.py
ngenctl/scripts/ngectl-rancher
ngenctl-0.1.14.dist-info/METADATA
ngenctl-0.1.14.dist-info/WHEEL
ngenctl-0.1.14.dist-info/entry_points.txt
ngenctl-0.1.14.dist-info/top_level.txt
ngenctl-0.1.14.dist-info/RECORD
