Metadata-Version: 2.4
Name: ngenctl
Version: 0.1.14
Summary: Universal command wrapper package that dispatches to /usr/local/bin/ngenctl-* scripts
Author: ngenctl contributors
License-Expression: MIT
Project-URL: Homepage, https://github.com/mamatnurahmat/ngenctl
Project-URL: Repository, https://github.com/mamatnurahmat/ngenctl
Project-URL: Issues, https://github.com/mamatnurahmat/ngenctl/issues
Keywords: cli,wrapper,command,dispatch
Classifier: Development Status :: 3 - Alpha
Classifier: Intended Audience :: Developers
Classifier: Programming Language :: Python :: 3
Classifier: Programming Language :: Python :: 3.7
Classifier: Programming Language :: Python :: 3.8
Classifier: Programming Language :: Python :: 3.9
Classifier: Programming Language :: Python :: 3.10
Classifier: Programming Language :: Python :: 3.11
Requires-Python: >=3.7
